vllm_autoconfig/__init__.py
vllm_autoconfig/cache.py
vllm_autoconfig/client.py
vllm_autoconfig/embedding.py
vllm_autoconfig/gpu_probe.py
vllm_autoconfig/kv_math.py
vllm_autoconfig/logits_processors.py
vllm_autoconfig/model_probe.py
vllm_autoconfig/planner.py
vllm_autoconfig/prompt_utils.py
vllm_speculative_autoconfig-0.2.10.dist-info/licenses/LICENSE
vllm_speculative_autoconfig-0.2.10.dist-info/METADATA
vllm_speculative_autoconfig-0.2.10.dist-info/WHEEL
vllm_speculative_autoconfig-0.2.10.dist-info/top_level.txt
vllm_speculative_autoconfig-0.2.10.dist-info/RECORD
