Metadata-Version: 2.4
Name: vllm-speculative-autoconfig
Version: 0.2.10
Summary: Automatic configuration planner for vLLM - Eliminate the guesswork of configuring vLLM by automatically determining optimal parameters
Author: Benaya Trabelsi
Maintainer: Benaya Trabelsi
License: MIT
Project-URL: Homepage, https://github.com/benayat/vllm-speculative-init
Project-URL: Repository, https://github.com/benayat/vllm-speculative-init
Project-URL: Issues, https://github.com/benayat/vllm-speculative-init/issues
Classifier: Development Status :: 3 - Alpha
Classifier: Intended Audience :: Developers
Classifier: License :: OSI Approved :: MIT License
Classifier: Programming Language :: Python :: 3
Classifier: Programming Language :: Python :: 3.10
Classifier: Programming Language :: Python :: 3.11
Classifier: Programming Language :: Python :: 3.12
Classifier: Topic :: Scientific/Engineering :: Artificial Intelligence
Requires-Python: >=3.10
License-File: LICENSE
Requires-Dist: torch>=2.0.0
Requires-Dist: transformers>=4.30.0
Requires-Dist: huggingface-hub>=0.16.0
Requires-Dist: vllm>=0.14.0
Requires-Dist: project-to-markdown>=0.1.6
Dynamic: license-file
